amok/__init__.py
amok/action.py
amok/base.py
amok/lib.py
amok/option.py
amok/utils.py
amok/config/__init__.py
amok/config/parsers.py
amok-0.1.1.dist-info/licenses/LICENSE.txt
amok-0.1.1.dist-info/METADATA
amok-0.1.1.dist-info/WHEEL
amok-0.1.1.dist-info/top_level.txt
amok-0.1.1.dist-info/RECORD
