Metadata-Version: 2.4
Name: amok
Version: 0.1.1
Summary: Create OpenAI API Compatible, Task driven agents.
Author-email: rapidclock <rapidclock@users.noreply.github.com>
Project-URL: Homepage, https://github.com/rapidclock/amok
Project-URL: Repository, https://github.com/rapidclock/amok
Classifier: Programming Language :: Python :: 3
Classifier: Operating System :: OS Independent
Requires-Python: >=3.12
License-File: LICENSE.txt
Requires-Dist: openai==1.97.0
Requires-Dist: httpx==0.28.1
Requires-Dist: PyYAML==6.0.2
Provides-Extra: dev
Requires-Dist: black==25.1.0; extra == "dev"
Requires-Dist: ruff==0.12.3; extra == "dev"
Requires-Dist: pytest==8.4.1; extra == "dev"
Requires-Dist: pytest-cov==6.2.1; extra == "dev"
Dynamic: license-file
